<?xml version="1.0" encoding="Shift_JIS" standalone="no"?>
<BlockWebservicesInfo>
	<ResultCode>00</ResultCode>
	<MailCount>2</MailCount>
	<FormatType>01</FormatType>
	<Mail>
		<MailInfo>
			<TrackingNoTypeCode>4</TrackingNoTypeCode>
			<TrackingNoType>国際郵便物</TrackingNoType>
			<TrackingNo>CI060662491JP   </TrackingNo>
			<MailClassCode>2120</MailClassCode>
			<MailClass>国際小包</MailClass>
			<LastHandlingDate>20150602</LastHandlingDate>
			<LastHandlingTime>1448</LastHandlingTime>
			<LastStatusCode>5201</LastStatusCode>
			<LastStatus>お届け済み</LastStatus>
			<LastEntCode>CCCN</LastEntCode>
			<LastShopCode>330038</LastShopCode>
			<LastShopName></LastShopName>
			<LastPostCode></LastPostCode>
			<LastCityCode></LastCityCode>
			<LastCityName>CHINA</LastCityName>
		</MailInfo>
		<Handling>
			<HandlingInfo>
				<HandlingDate>20150511</HandlingDate>
				<HandlingTime>1219</HandlingTime>
				<StatusCode>1101</StatusCode>
				<Status>引受</Status>
				<StatusDetail></StatusDetail>
				<EntCode>2001</EntCode>
				<ShopCode>220020</ShopCode>
				<ShopName>四日市郵便局</ShopName>
				<PostCode>510-8799</PostCode>
				<CityCode></CityCode>
				<CityName>三重県</CityName>
			</HandlingInfo>
			<HandlingInfo>
				<HandlingDate>20150512</HandlingDate>
				<HandlingTime>1109</HandlingTime>
				<StatusCode>7082</StatusCode>
				<Status>国際交換局に到着</Status>
				<StatusDetail></StatusDetail>
				<EntCode>2001</EntCode>
				<ShopCode>090730</ShopCode>
				<ShopName>川崎東郵便局</ShopName>
				<PostCode>219-8799</PostCode>
				<CityCode></CityCode>
				<CityName>神奈川県</CityName>
			</HandlingInfo>
			<HandlingInfo>
				<HandlingDate>20150512</HandlingDate>
				<HandlingTime>1158</HandlingTime>
				<StatusCode>7080</StatusCode>
				<Status>国際交換局から発送</Status>
				<StatusDetail></StatusDetail>
				<EntCode>2001</EntCode>
				<ShopCode>090730</ShopCode>
				<ShopName>川崎東郵便局</ShopName>
				<PostCode>219-8799</PostCode>
				<CityCode></CityCode>
				<CityName>神奈川県</CityName>
			</HandlingInfo>
			<HandlingInfo>
				<HandlingDate>20150531</HandlingDate>
				<HandlingTime>1420</HandlingTime>
				<StatusCode>7083</StatusCode>
				<Status>国際交換局に到着</Status>
				<StatusDetail></StatusDetail>
				<EntCode>CCCN</EntCode>
				<ShopCode>CNSHAA</ShopCode>
				<ShopName>SHANGHAI</ShopName>
				<PostCode></PostCode>
				<CityCode></CityCode>
				<CityName>CHINA</CityName>
			</HandlingInfo>
			<HandlingInfo>
				<HandlingDate>20150602</HandlingDate>
				<HandlingTime>1448</HandlingTime>
				<StatusCode>5201</StatusCode>
				<Status>お届け済み</Status>
				<StatusDetail></StatusDetail>
				<EntCode>CCCN</EntCode>
				<ShopCode>330038</ShopCode>
				<ShopName></ShopName>
				<PostCode></PostCode>
				<CityCode></CityCode>
				<CityName>CHINA</CityName>
			</HandlingInfo>
		</Handling>
	</Mail>
	<Mail>
		<MailInfo>
			<TrackingNoTypeCode>4</TrackingNoTypeCode>
			<TrackingNoType>国際郵便物</TrackingNoType>
			<TrackingNo>223456789012    </TrackingNo>
		</MailInfo>
	</Mail>
</BlockWebservicesInfo>
